literate_python/__init__.py
literate_python/__main__.py
literate_python/inspector.py
literate_python/loader.py
literate_python/reloader.py
literate_python/sections.py
literate_python/server.py
literate_python/tests/test_hot_reload.py
literate_python/tests/test_server.py
literate_python-0.0.6.dist-info/LICENSE
literate_python-0.0.6.dist-info/METADATA
literate_python-0.0.6.dist-info/WHEEL
literate_python-0.0.6.dist-info/RECORD
