Metadata-Version: 2.3
Name: literate_python
Version: 0.0.6
Summary: Develop Python modules in Org files.
License: MIT License
Author: Jingtao Xu
Author-email: jingtaozf@gmail.com
Requires-Python: >=3.8
Classifier: Operating System :: OS Independent
Classifier: Environment :: Console
Classifier: Intended Audience :: Developers
Classifier: Programming Language :: Python
Classifier: Programming Language :: Python :: 3.8
Classifier: Programming Language :: Python :: 3.9
Classifier: Programming Language :: Python :: 3.10
Classifier: Programming Language :: Python :: 3.11
Classifier: Programming Language :: Python :: 3 :: Only
Requires-Dist: flask
Requires-Dist: multimethod
Requires-Dist: orgparse
Requires-Dist: packaging
Project-URL: Homepage, https://github.com/jingtaozf/literate-org
